homi/__init__.py
homi/__main__.py
homi/app.py
homi/cli.py
homi/config.py
homi/exception.py
homi/proto_meta.py
homi/server.py
homi/test_case.py
homi/aio/__init__.py
homi/aio/app.py
homi/aio/server.py
homi/extend/__init__.py
homi/extend/service.py
tests/simple_case/__init__.py
tests/simple_case/app.py
tests/simple_case/async_app.py
tests/simple_case/helloworld_pb2.py
tests/simple_case/helloworld_pb2_grpc.py
tests/simple_case/test_async_simple_case.py
tests/simple_case/test_health_service.py
tests/simple_case/test_simple_case.py
tests/test_alts/__init__.py
tests/test_alts/app.py
tests/test_alts/helloworld_pb2.py
tests/test_alts/helloworld_pb2_grpc.py
tests/test_alts/test_alts.py
tests/test_tls/__init__.py
tests/test_tls/app.py
tests/test_tls/helloworld_pb2.py
tests/test_tls/helloworld_pb2_grpc.py
tests/test_tls/test_tls.py
tests/test_to_dict/__init__.py
tests/test_to_dict/app.py
tests/test_to_dict/helloworld_pb2.py
tests/test_to_dict/helloworld_pb2_grpc.py
tests/test_to_dict/test_to_dict.py
homi-0.2.2.dist-info/LICENSE
homi-0.2.2.dist-info/METADATA
homi-0.2.2.dist-info/WHEEL
homi-0.2.2.dist-info/entry_points.txt
homi-0.2.2.dist-info/top_level.txt
homi-0.2.2.dist-info/RECORD
