Metadata-Version: 2.1
Name: homi
Version: 0.2.2
Summary: micro grpc framework like flask
Home-page: https://github.com/spaceone-dev/homi
Maintainer: MEGAZONE SpaceONE Team
Maintainer-email: admin@spaceone.dev
License: Apache License 2.0
Platform: UNKNOWN
Classifier: Intended Audience :: Developers
Classifier: Operating System :: OS Independent
Classifier: Programming Language :: Python
Classifier: Programming Language :: Python :: 3
Classifier: Programming Language :: Python :: 3 :: Only
Classifier: Programming Language :: Python :: 3.6
Classifier: Programming Language :: Python :: 3.7
Classifier: Programming Language :: Python :: 3.8
Classifier: Topic :: Software Development :: Libraries :: Python Modules
Classifier: Topic :: Software Development :: Libraries :: Application Frameworks
Requires-Python: >=3.6
Requires-Dist: grpcio (>=1.34.0)
Requires-Dist: grpcio-reflection (>=1.34.0)
Requires-Dist: grpcio-health-checking (>=1.34.0)
Requires-Dist: grpcio-testing (>=1.30.0)
Requires-Dist: google-api-core (>=1.24.1)
Requires-Dist: click (==7.1.2)
Requires-Dist: cryptography (>=3.1.1)
Requires-Dist: uvloop (>=0.14.0)
Requires-Dist: typing-extensions (>=3.7.4.3)
